{
  "rasa_nlu_data": {
    "common_examples": [
      {
        "intent": "add_medicine",
        "text": "เพิ่มยา"
      },
      {
        "intent": "add_medicine",
        "text": "add medicine"
      },
      {
        "intent": "add_medicine",
        "text": "add drug"
      },
      {
        "intent": "add_medicine",
        "text": "ยาใหม่"
      },
      {
        "intent": "add_medicine",
        "text": "เพิ่มยาใหม่"
      },
      {
        "intent": "add_medicine",
        "text": "บันทึกยา"
      },
      {
        "intent": "add_medicine",
        "text": "add new drug"
      },
      {
        "intent": "add_medicine",
        "text": "แอดยา"
      },
      {
        "intent": "enter_medicine_data",
        "entities": [
          {
            "start": 0,
            "end": 9,
            "value": "before_meal",
            "entity": "medicine_meal"
          }
        ],
        "text": "ก่อนอาหาร"
      },
      {
        "intent": "enter_medicine_data",
        "entities": [
          {
            "start": 0,
            "end": 9,
            "value": "after_meal",
            "entity": "medicine_meal"
          }
        ],
        "text": "หลังอาหาร"
      },
      {
        "intent": "enter_medicine_data",
        "entities": [
          {
            "start": 0,
            "end": 4,
            "value": "morning",
            "entity": "medicine_time"
          }
        ],
        "text": "เช้า"
      },
      {
        "intent": "enter_medicine_data",
        "entities": [
          {
            "start": 0,
            "end": 7,
            "value": "morning",
            "entity": "medicine_time"
          }
        ],
        "text": "morning"
      },
      {
        "intent": "enter_medicine_data",
        "entities": [
          {
            "start": 0,
            "end": 7,
            "value": "noon",
            "entity": "medicine_time"
          }
        ],
        "text": "กลางวัน"
      },
      {
        "intent": "enter_medicine_data",
        "entities": [
          {
            "start": 0,
            "end": 4,
            "value": "noon",
            "entity": "medicine_time"
          }
        ],
        "text": "noon"
      },
      {
        "intent": "enter_medicine_data",
        "entities": [
          {
            "start": 0,
            "end": 5,
            "value": "noon",
            "entity": "medicine_time"
          }
        ],
        "text": "lunch"
      },
      {
        "intent": "enter_medicine_data",
        "entities": [
          {
            "start": 0,
            "end": 6,
            "value": "noon",
            "entity": "medicine_time"
          }
        ],
        "text": "เที่ยง"
      },
      {
        "intent": "enter_medicine_data",
        "entities": [
          {
            "start": 0,
            "end": 4,
            "value": "evening",
            "entity": "medicine_time"
          }
        ],
        "text": "เย็น"
      },
      {
        "intent": "enter_medicine_data",
        "entities": [
          {
            "start": 0,
            "end": 6,
            "value": "evening",
            "entity": "medicine_time"
          }
        ],
        "text": "dinner"
      },
      {
        "intent": "enter_medicine_data",
        "entities": [
          {
            "start": 0,
            "end": 7,
            "value": "evening",
            "entity": "medicine_time"
          }
        ],
        "text": "evening"
      },
      {
        "intent": "enter_medicine_data",
        "entities": [
          {
            "start": 0,
            "end": 8,
            "value": "evening",
            "entity": "medicine_time"
          }
        ],
        "text": "ตอน เย็น"
      },
      {
        "intent": "enter_medicine_data",
        "entities": [
          {
            "start": 0,
            "end": 9,
            "value": "evening",
            "entity": "medicine_time"
          }
        ],
        "text": "มื้อ เย็น"
      },
      {
        "intent": "enter_medicine_data",
        "entities": [
          {
            "start": 0,
            "end": 7,
            "value": "evening",
            "entity": "medicine_time"
          }
        ],
        "text": "พลบ ค่ำ"
      },
      {
        "intent": "enter_medicine_data",
        "entities": [
          {
            "start": 0,
            "end": 3,
            "value": "evening",
            "entity": "medicine_time"
          }
        ],
        "text": "ค่ำ"
      },
      {
        "intent": "enter_medicine_data",
        "entities": [
          {
            "start": 0,
            "end": 8,
            "value": "night",
            "entity": "medicine_time"
          }
        ],
        "text": "ก่อน นอน"
      },
      {
        "intent": "enter_medicine_data",
        "entities": [
          {
            "start": 0,
            "end": 5,
            "value": "night",
            "entity": "medicine_time"
          }
        ],
        "text": "night"
      },
      {
        "intent": "enter_medicine_data",
        "entities": [
          {
            "start": 0,
            "end": 8,
            "value": "night",
            "entity": "medicine_time"
          }
        ],
        "text": "bed time"
      },
      {
        "intent": "enter_medicine_data",
        "entities": [
          {
            "start": 0,
            "end": 12,
            "value": "night",
            "entity": "medicine_time"
          }
        ],
        "text": "before sleep"
      },
      {
        "intent": "enter_medicine_data",
        "entities": [
          {
            "start": 0,
            "end": 17,
            "value": "morning_noon_evening",
            "entity": "medicine_time"
          }
        ],
        "text": "เช้า กลางวัน เย็น"
      },
      {
        "intent": "enter_medicine_data",
        "entities": [
          {
            "start": 0,
            "end": 17,
            "value": "morning_noon_evening",
            "entity": "medicine_time"
          }
        ],
        "text": "three times a day"
      },
      {
        "intent": "enter_medicine_data",
        "entities": [
          {
            "start": 0,
            "end": 13,
            "value": "morning_noon_evening",
            "entity": "medicine_time"
          }
        ],
        "text": "3 times a day"
      },
      {
        "intent": "enter_medicine_data",
        "entities": [
          {
            "start": 0,
            "end": 7,
            "value": "morning_noon_evening",
            "entity": "medicine_time"
          }
        ],
        "text": "3 meals"
      },
      {
        "intent": "enter_medicine_data",
        "entities": [
          {
            "start": 0,
            "end": 8,
            "value": "morning_noon_evening",
            "entity": "medicine_time"
          }
        ],
        "text": "สาม เวลา"
      },
      {
        "intent": "enter_medicine_data",
        "entities": [
          {
            "start": 0,
            "end": 9,
            "value": "morning_evening",
            "entity": "medicine_time"
          }
        ],
        "text": "เช้า เย็น"
      },
      {
        "intent": "enter_medicine_data",
        "entities": [
          {
            "start": 0,
            "end": 8,
            "value": "morning_noon_evening_night",
            "entity": "medicine_time"
          }
        ],
        "text": "สี่ เวลา"
      },
      {
        "intent": "enter_medicine_data",
        "entities": [
          {
            "start": 0,
            "end": 25,
            "value": "morning_noon_evening_night",
            "entity": "medicine_time"
          }
        ],
        "text": "เช้า กลางวัน เย็น ก่อนนอน"
      },
      {
        "intent": "medicine_list",
        "text": "รายการยา"
      },
      {
        "intent": "medicine_list",
        "text": "รายชื่อยา"
      },
      {
        "intent": "medicine_list",
        "text": "ลิสต์ยา"
      },
      {
        "intent": "medicine_list",
        "text": "drug list"
      },
      {
        "intent": "medicine_list",
        "text": "medicine list"
      },
      {
        "intent": "medicine_list",
        "text": "medication list"
      },
      {
        "intent": "affirmative",
        "text": "ใช่"
      },
      {
        "intent": "affirmative",
        "text": "ใช่ เพิ่มยาใหม่"
      },
      {
        "intent": "affirmative",
        "text": "ทานแล้ว"
      },
      {
        "intent": "affirmative",
        "text": "เรียบร้อย"
      },
      {
        "intent": "affirmative",
        "text": "ถูกต้อง"
      },
      {
        "intent": "affirmative",
        "text": "ใช่เลย"
      },
      {
        "intent": "negative",
        "text": "ไม่"
      },
      {
        "intent": "negative",
        "text": "ไม่มี"
      },
      {
        "intent": "negative",
        "text": "ไม่เอา"
      },
      {
        "intent": "negative",
        "text": "ยกเลิก"
      },
      {
        "intent": "negative",
        "text": "ยังเลย"
      },
      {
        "intent": "negative",
        "text": "ยังไม่ทาน"
      },
      {
        "intent": "negative",
        "text": "ยังไม่ได้ทานเลย"
      },
      {
        "intent": "greeting",
        "text": "hi"
      },
      {
        "intent": "greeting",
        "text": "hey"
      },
      {
        "intent": "greeting",
        "text": "สวัสดี"
      },
      {
        "intent": "greeting",
        "text": "สวัสดีค่ะ"
      },
      {
        "intent": "greeting",
        "text": "สวัสดีครับ"
      },
      {
        "intent": "greeting",
        "text": "หวัดดี"
      },
      {
        "intent": "greeting",
        "text": "ดี"
      },
      {
        "intent": "greeting",
        "text": "โย่ว"
      },
      {
        "intent": "greeting",
        "text": "ฮัลโหล"
      },
      {
        "intent": "greeting",
        "text": "ฮาโหล"
      },
      {
        "intent": "greeting",
        "text": "hello"
      },
      {
        "intent": "greeting",
        "text": "good morning"
      },
      {
        "intent": "greeting",
        "text": "good afternoon"
      },
      {
        "intent": "greeting",
        "text": "good evening"
      },
      {
        "intent": "greeting",
        "text": "อรุณสวัสดิ์"
      },
      {
        "intent": "howto",
        "text": "ดูวิธีใช้"
      },
      {
        "intent": "howto",
        "text": "วิธีใช้"
      },
      {
        "intent": "howto",
        "text": "ใช้ยังไง"
      },
      {
        "intent": "howto",
        "text": "ช่วยเหลือ"
      },
      {
        "intent": "howto",
        "text": "การใช้งาน"
      },
      {
        "intent": "sleep",
        "text": "ง่วง"
      },
      {
        "intent": "sleep",
        "text": "ง่วงจัง"
      },
      {
        "intent": "sleep",
        "text": "ง่วงนอน"
      },
      {
        "intent": "sleep",
        "text": "นอน"
      },
      {
        "intent": "sleep",
        "text": "ตาจะปิดแล้ว"
      },
      {
        "intent": "sleep",
        "text": "หลับ"
      },
      {
        "intent": "lazy",
        "text": "ขี้เกียจ"
      },
      {
        "intent": "lazy",
        "text": "ขี้เกียด"
      },
      {
        "intent": "lazy",
        "text": "ขี้เกียจจัง"
      },
      {
        "intent": "hungry",
        "text": "หิว"
      },
      {
        "intent": "hungry",
        "text": "หิวมาก"
      },
      {
        "intent": "hungry",
        "text": "วันนี้ยังไม่ได้กินอะไรเลย"
      },
      {
        "intent": "hungry",
        "text": "กินอะไรดีวันนี้"
      },
      {
        "intent": "hungry",
        "text": "เที่ยงนี้กินอะไรดี"
      },
      {
        "intent": "hungry",
        "text": "เช้านี้กินอะไรดี"
      },
      {
        "intent": "hungry",
        "text": "เย็นนี้กินอะไรดี"
      },
      {
        "intent": "hungry",
        "text": "หิวข้าวจัง"
      },
      {
        "intent": "hungry",
        "text": "อยากกินข้าว"
      },
      {
        "intent": "hungry",
        "text": "หิวจัง"
      },
      {
        "intent": "tired",
        "text": "เหนื่อยมากวันนี้"
      },
      {
        "intent": "tired",
        "text": "เหนื่อยจัง"
      },
      {
        "intent": "tired",
        "text": "เหนื่อย"
      },
      {
        "intent": "tired",
        "text": "วันนี้เหนื่อย"
      },
      {
        "intent": "tired",
        "text": "ท้อจัง"
      },
      {
        "intent": "tired",
        "text": "งานเหนื่อย"
      },
      {
        "intent": "tired",
        "text": "งานหนัก"
      }
    ],
    "regex_features": [],
    "lookup_tables": [],
    "entity_synonyms": [
      {
        "value": "before_meal",
        "synonyms": [
          "ก่อนอาหาร"
        ]
      },
      {
        "value": "after_meal",
        "synonyms": [
          "หลังอาหาร"
        ]
      },
      {
        "value": "morning",
        "synonyms": [
          "เช้า"
        ]
      },
      {
        "value": "noon",
        "synonyms": [
          "กลางวัน",
          "lunch",
          "เที่ยง"
        ]
      },
      {
        "value": "evening",
        "synonyms": [
          "เย็น",
          "dinner",
          "ตอน เย็น",
          "มื้อ เย็น",
          "พลบ ค่ำ",
          "ค่ำ"
        ]
      },
      {
        "value": "night",
        "synonyms": [
          "ก่อน นอน",
          "bed time",
          "before sleep"
        ]
      },
      {
        "value": "morning_noon_evening",
        "synonyms": [
          "เช้า กลางวัน เย็น",
          "three times a day",
          "3 times a day",
          "3 meals",
          "สาม เวลา"
        ]
      },
      {
        "value": "morning_evening",
        "synonyms": [
          "เช้า เย็น"
        ]
      },
      {
        "value": "morning_noon_evening_night",
        "synonyms": [
          "สี่ เวลา",
          "เช้า กลางวัน เย็น ก่อนนอน"
        ]
      }
    ]
  }
}